Metadata-Version: 1.1
Name: rucio-arc
Version: 0.0.6
Summary: rucio-arc is an extension for Rucio, e.g., ARC data delivery service
Home-page: UNKNOWN
Author: Rucio
Author-email: UNKNOWN
License: Apache License, Version 2.0
Platform: UNKNOWN
Classifier: Development Status :: 5 - Production/Stable
Classifier: License :: OSI Approved :: Apache Software License
Classifier: Intended Audience :: Information Technology
Classifier: Intended Audience :: System Administrators
Classifier: Operating System :: POSIX :: Linux
Classifier: Natural Language :: English
Classifier: Programming Language :: Python
Classifier: Programming Language :: Python :: 2.7
Classifier: Environment :: No Input/Output (Daemon)
